zwdoc/__init__.py
zwdoc/__version__.py
zwdoc/excel.py
zwdoc-0.1.1.dist-info/LICENSE
zwdoc-0.1.1.dist-info/METADATA
zwdoc-0.1.1.dist-info/WHEEL
zwdoc-0.1.1.dist-info/top_level.txt
zwdoc-0.1.1.dist-info/RECORD
