Metadata-Version: 2.1
Name: zwdoc
Version: 0.1.1
Summary: Personal Python Utilities
Home-page: https://github.com/njzhaowei/zwdoc
Author: Zhao Wei
Author-email: yewberry@163.com
License: Apache 2.0
Platform: all
Classifier: Programming Language :: Python :: 3
Classifier: License :: OSI Approved :: Apache Software License
Classifier: Operating System :: OS Independent
Requires-Python: >=3.6
License-File: LICENSE
Requires-Dist: loguru
Requires-Dist: openpyxl
